stack_data/__init__.py
stack_data/core.py
stack_data/formatting.py
stack_data/py.typed
stack_data/serializing.py
stack_data/utils.py
stack_data/version.py
stack_data-0.6.1.dist-info/LICENSE.txt
stack_data-0.6.1.dist-info/METADATA
stack_data-0.6.1.dist-info/WHEEL
stack_data-0.6.1.dist-info/top_level.txt
stack_data-0.6.1.dist-info/RECORD
